vercel_ai.py
vercel_llm_api-0.3.0.dist-info/LICENSE
vercel_llm_api-0.3.0.dist-info/METADATA
vercel_llm_api-0.3.0.dist-info/WHEEL
vercel_llm_api-0.3.0.dist-info/top_level.txt
vercel_llm_api-0.3.0.dist-info/RECORD
