Metadata-Version: 2.1
Name: vercel-llm-api
Version: 0.3.0
Summary: A reverse engineered API for the Vercel AI playground.
Home-page: https://github.com/ading2210/vercel-llm-api
Author: ading2210
License: GPLv3
Classifier: Programming Language :: Python :: 3
Classifier: License :: OSI Approved :: GNU General Public License (GPL)
Classifier: Operating System :: OS Independent
Requires-Python: >=3.7
License-File: LICENSE
Requires-Dist: curl-cffi
Requires-Dist: quickjs
